CHANGELOG.txt
LICENSE.txt
MANIFEST.in
README.txt
ez_setup.py
setup.cfg
setup.py
PipeStack.egg-info/PKG-INFO
PipeStack.egg-info/SOURCES.txt
PipeStack.egg-info/dependency_links.txt
PipeStack.egg-info/entry_points.txt
PipeStack.egg-info/not-zip-safe
PipeStack.egg-info/requires.txt
PipeStack.egg-info/top_level.txt
doc/Makefile
doc/index.txt
doc/source/api.rst
doc/source/conf.py
doc/source/index.rst
doc/source/manual.rst
doc/source/psgi.rst
example/README.txt
example/log_example.py
pipestack/__init__.py
pipestack/app.py
pipestack/ensure.py
pipestack/migrate.py
pipestack/pipe.py
pipestack/test/__init__.py
pipestack/test/basic.py
test/README.txt
test/doc.py