Metadata-Version: 1.0
Name: PipeStack
Version: 0.5.3
Summary: A new methodology for structuring applications based on the concepts of a stack of pipes, and a bag of marbles. Not ready for public use yet, but getting there fast.
Home-page: http://jimmyg.org/work/code/pipestack/index.html
Author: James Gardner
Author-email: james@<package hompage domain>
License: GNU AGPLv3
Platform: UNKNOWN
Classifier: Development Status :: 3 - Alpha
Classifier: License :: OSI Approved :: GNU Affero General Public License v3
Classifier: Programming Language :: Python
